attitude/__init__.py
attitude/bingham.py
attitude/stereonet.py
attitude/coordinates/__init__.py
attitude/coordinates/rotations.py
attitude/display/__init__.py
attitude/display/cartopy.py
attitude/display/error_comparison.py
attitude/display/hyperbola.py
attitude/display/nbextension.py
attitude/display/parametric.py
attitude/display/pca_aligned.py
attitude/display/polar.py
attitude/display/stereonet.py
attitude/display/test_display.py
attitude/display/test_hyperbolic_errors.py
attitude/display/test_plots.py
attitude/display/util.py
attitude/display/lib/attitude-ui.js
attitude/display/lib/attitude.js
attitude/display/lib/attitude.node.js
attitude/display/lib/core.bundle.js
attitude/display/lib/d3-selection-multi.min.js
attitude/display/lib/d3v4+jetpack.js
attitude/display/lib/math.js
attitude/display/lib/math.min.js
attitude/display/lib/styles.css
attitude/display/lib/ui-styles.css
attitude/display/plot/__init__.py
attitude/display/plot/component_planes.py
attitude/display/plot/misc.py
attitude/display/plot/cov_types/__init__.py
attitude/display/plot/cov_types/misc.py
attitude/display/plot/cov_types/regressions.py
attitude/error/__init__.py
attitude/error/axes.py
attitude/error/bootstrap.py
attitude/error/ellipse.py
attitude/geom/__init__.py
attitude/geom/conics.py
attitude/geom/symbolic_math.py
attitude/geom/test_conics.py
attitude/geom/test_errors.py
attitude/geom/test_geom.py
attitude/geom/test_hyperbolic_errors.py
attitude/geom/test_offset_ellipse.py
attitude/geom/transform.py
attitude/geom/util.py
attitude/helpers/__init__.py
attitude/helpers/dem.py
attitude/helpers/interpolation.py
attitude/orientation/__init__.py
attitude/orientation/base.py
attitude/orientation/grouped.py
attitude/orientation/pca.py
attitude/orientation/reconstructed.py
attitude/orientation/test_pca.py
attitude/orientation/test_reconstructed.py
attitude/orientation/tests.py
attitude/orientation/linear/__init__.py
attitude/orientation/linear/regression.py
attitude/orientation/linear/tests.py
Attitude-0.5.0.dist-info/LICENSE.md
Attitude-0.5.0.dist-info/METADATA
Attitude-0.5.0.dist-info/WHEEL
Attitude-0.5.0.dist-info/top_level.txt
Attitude-0.5.0.dist-info/RECORD
