Metadata-Version: 2.1
Name: Attitude
Version: 0.5.0
Summary: Attitude computes the orientations of planes from point data.
Home-page: http://github.com/davenquinn/Attitude
Author: Daven Quinn
Author-email: code@davenquinn.com
Maintainer: Daven Quinn
Maintainer-email: code@davenquinn.com
License: MIT
Keywords: gis data computation fitting statistics vector science geology
Platform: UNKNOWN
Classifier: Development Status :: 2 - Pre-Alpha
Classifier: Intended Audience :: Science/Research
Classifier: Operating System :: OS Independent
Classifier: Programming Language :: Python
Classifier: Topic :: Scientific/Engineering :: GIS
Requires-Dist: numpy
Requires-Dist: scipy
Requires-Dist: matplotlib
Requires-Dist: mplstereonet
Requires-Dist: jinja2
Requires-Dist: colour
Requires-Dist: pytest
Requires-Dist: pytest-mpl
Requires-Dist: IPython
Requires-Dist: subdivide (>=1)
